mycustomls/__init__.py
mycustomls/main.py
mycustomls-0.1.0.dist-info/METADATA
mycustomls-0.1.0.dist-info/WHEEL
mycustomls-0.1.0.dist-info/entry_points.txt
mycustomls-0.1.0.dist-info/RECORD
